InputValidation/ValidateInput.py
InputValidation/__init__.py
validateInput/ValidateInput.py
validateInput/__init__.py
ValidateInput-0.0.1.dist-info/LICENSE.txt
ValidateInput-0.0.1.dist-info/METADATA
ValidateInput-0.0.1.dist-info/WHEEL
ValidateInput-0.0.1.dist-info/top_level.txt
ValidateInput-0.0.1.dist-info/RECORD
