Metadata-Version: 2.1
Name: ValidateInput
Version: 0.0.1
Summary: A module that validates whether the input text is a string or an integer
Home-page: https://github.com/6outtaTen/validateInput
Author: 6outtaTen
Author-email: jacol.mucha@gmail.com
License: UNKNOWN
Platform: UNKNOWN
Classifier: Programming Language :: Python :: 3
Classifier: License :: OSI Approved :: MIT License
Classifier: Operating System :: OS Independent
Requires-Python: >=3.6
